MANIFEST.in
README.rst
setup.cfg
setup.py
pycanvass/__init__.py
pycanvass/all.py
pycanvass/blocks.py
pycanvass/complexnetwork.py
pycanvass/data_bridge.py
pycanvass/data_visualization.py
pycanvass/distributionsystem.py
pycanvass/eventloop.py
pycanvass/fault_tree_anlaysis.py
pycanvass/forecast.py
pycanvass/global_variables.py
pycanvass/metric.py
pycanvass/optimizer.py
pycanvass/parsexmlcode.py
pycanvass/resiliency.py
pycanvass/spanningtree.py
pycanvass/utilities.py
pycanvass/xml_analysis.py