Metadata-Version: 2.1
Name: pycanvass
Version: 0.0.2.23
Summary: Python API for Cyber Attack and Network Vulnerability Assessment Software for Smartgrid
Home-page: http://github.com/sayonsom/pycanvass
Author: Sayonsom Chanda
Author-email: sayon@ieee.org
License: GPL
Keywords: smartgrid power system substation cyber-attack simulation rtds gridlabd python
Platform: UNKNOWN
Classifier: Development Status :: 3 - Alpha
Classifier: License :: OSI Approved :: GNU General Public License v2 (GPLv2)
Classifier: Intended Audience :: Science/Research
Classifier: Programming Language :: Python :: 3.6
Classifier: Topic :: Scientific/Engineering :: Artificial Intelligence
Provides-Extra: test
